maskbit_pytorch/__init__.py
maskbit_pytorch/maskbit.py
maskbit_pytorch/trainer.py
maskbit_pytorch-0.0.2.dist-info/METADATA
maskbit_pytorch-0.0.2.dist-info/WHEEL
maskbit_pytorch-0.0.2.dist-info/licenses/LICENSE
maskbit_pytorch-0.0.2.dist-info/RECORD
