Metadata-Version: 2.3
Name: maskbit-pytorch
Version: 0.0.2
Summary: MaskBit
Project-URL: Homepage, https://pypi.org/project/maskbit-pytorch/
Project-URL: Repository, https://github.com/lucidrains/maskbit-pytorch
Author-email: Phil Wang <lucidrains@gmail.com>
License: MIT License
Keywords: artificial intelligence,attention mechanism,deep learning,image generation,scalar quantization,transformers
Classifier: Development Status :: 4 - Beta
Classifier: Intended Audience :: Developers
Classifier: License :: OSI Approved :: MIT License
Classifier: Programming Language :: Python :: 3.9
Classifier: Topic :: Scientific/Engineering :: Artificial Intelligence
Requires-Python: >=3.9
Requires-Dist: accelerate
Requires-Dist: adam-atan2-pytorch>=0.1.1
Requires-Dist: beartype
Requires-Dist: einops>=0.8.0
Requires-Dist: einx>=0.3.0
Requires-Dist: ema-pytorch
Requires-Dist: jaxtyping
Requires-Dist: pillow
Requires-Dist: torch>=2.2
Requires-Dist: torchvision
Requires-Dist: vector-quantize-pytorch>=1.17.8
Requires-Dist: x-transformers>=1.37.9
Provides-Extra: examples
Provides-Extra: test
Requires-Dist: pytest; extra == 'test'
